moht/__init__.py
moht/default.yaml
moht/log.py
moht/py.typed
moht/qtgui.py
moht/qtgui_rc.py
moht/start.py
moht/utils.py
moht/img/moht.ico
moht/img/moht.png
moht/resources/omwcmd-0.2.1
moht/resources/omwcmd-0.2.1.exe
moht/resources/tes3cmd-0.37v.exe
moht/resources/tes3cmd-0.37w
moht/resources/tes3cmd-0.40-pre_rel2
moht/resources/tes3cmd-0.40-pre_rel2.exe
moht-1.1.2.dist-info/licenses/LICENSE.md
moht-1.1.2.dist-info/METADATA
moht-1.1.2.dist-info/WHEEL
moht-1.1.2.dist-info/entry_points.txt
moht-1.1.2.dist-info/top_level.txt
moht-1.1.2.dist-info/RECORD
