Metadata-Version: 2.4
Name: moht
Version: 1.1.2
Summary: Simple yet powerful tool to help you manage your mods in several ways.
Author: Michal Plichta
Maintainer: Michal Plichta
License-Expression: MIT
Project-URL: Homepage, https://gitlab.com/modding-openmw/modhelpertool
Project-URL: Documentation, https://gitlab.com/modding-openmw/modhelpertool/-/blob/main/README.md
Project-URL: Source, https://gitlab.com/modding-openmw/modhelpertool.git
Project-URL: Changelog, https://gitlab.com/modding-openmw/modhelpertool/-/blob/main/CHANGELOG.md
Keywords: morrowind,openmw,mod,tes3cmd,modding,tes3
Classifier: Development Status :: 5 - Production/Stable
Classifier: Environment :: Console
Classifier: Environment :: MacOS X
Classifier: Environment :: Win32 (MS Windows)
Classifier: Environment :: X11 Applications
Classifier: Intended Audience :: End Users/Desktop
Classifier: Programming Language :: Python :: 3 :: Only
Classifier: Programming Language :: Python :: 3.9
Classifier: Programming Language :: Python :: 3.10
Classifier: Programming Language :: Python :: 3.11
Classifier: Programming Language :: Python :: 3.12
Classifier: Programming Language :: Python :: 3.13
Classifier: Operating System :: MacOS
Classifier: Operating System :: Microsoft :: Windows
Classifier: Operating System :: Microsoft :: Windows :: Windows 10
Classifier: Operating System :: POSIX :: Linux
Classifier: Topic :: Games/Entertainment
Classifier: Topic :: Games/Entertainment :: Role-Playing
Classifier: Topic :: Utilities
Requires-Python: >=3.10
License-File: LICENSE.md
Requires-Dist: packaging==24.2
Requires-Dist: PySide6==6.8.2.1
Requires-Dist: PyYAML==6.0.2
Requires-Dist: QtAwesome==1.4.0
Provides-Extra: test
Requires-Dist: interrogate==1.7.0; extra == "test"
Requires-Dist: lxml==5.3.1; extra == "test"
Requires-Dist: mypy==1.15.0; extra == "test"
Requires-Dist: pip-audit==2.8.0; extra == "test"
Requires-Dist: pytest==8.3.5; extra == "test"
Requires-Dist: pytest-qt==4.4.0; extra == "test"
Requires-Dist: pytest-randomly==3.16.0; extra == "test"
Requires-Dist: pytest-xvfb==3.1.1; extra == "test"
Requires-Dist: ruff==0.11.2; extra == "test"
Requires-Dist: tox==4.24.2; extra == "test"
Requires-Dist: types-PyYAML==6.0.12.20241230; extra == "test"
Provides-Extra: dev
Requires-Dist: build; extra == "dev"
Requires-Dist: detect-test-pollution; extra == "dev"
Requires-Dist: pre-commit; extra == "dev"
Requires-Dist: PySide6-stubs; extra == "dev"
Dynamic: license-file
